README.md
setup.cfg
setup.py
ibclient/__init__.py
ibclient/constants.py
ibclient/contract.py
ibclient/ib_client.py
ibclient/msg_wrapper.py
ibclient/orders.py
ibclient.egg-info/PKG-INFO
ibclient.egg-info/SOURCES.txt
ibclient.egg-info/dependency_links.txt
ibclient.egg-info/requires.txt
ibclient.egg-info/top_level.txt
ibclient/account/__init__.py
ibclient/account/account.py
ibclient/account/portfolio.py
ibclient/account/position.py
ibclient/parsers/__init__.py
ibclient/parsers/report_parsers.py
ibclient/utils/__init__.py
ibclient/utils/error_code.py
ibclient/utils/payload.py
tests/__init__.py
tests/account_test.py
tests/config.py
tests/fund_test.py
tests/history_test.py
tests/order_mgmt_test.py
tests/order_test.py
tests/tick_test.py