Metadata-Version: 1.1
Name: ibclient
Version: 0.0.3
Summary: A Python SDK to access market data through Interactive Brokers TWS
Home-page: https://github.com/chrjxj/ibclient
Author: Jin Xu
Author-email: jin_xu1@qq.com
License: BSD
Keywords: Interactive Brokers,TWS,IB,Stock,finance
Platform: UNKNOWN
Classifier: Development Status :: 3 - Alpha
Classifier: License :: OSI Approved :: BSD License
Classifier: Operating System :: OS Independent
Classifier: Programming Language :: Python
Classifier: Topic :: Software Development :: Libraries :: Python Modules
Classifier: Programming Language :: Python :: 2.7
Classifier: Programming Language :: Python :: 3.5
Classifier: Programming Language :: Python :: 3.6
Classifier: Programming Language :: Python :: 3.7
